{
  "source": {
    "type": "object",
    "propertyExpressions": [
      {
        "expression": {
          "type": "expression",
          "expression": "T(String).valueOf(object.stringAttr)"
        },
        "property": "stringAttr"
      },
      {
        "expression": {
          "type": "expression",
          "expression": "T(String).valueOf(object.intAttr)"
        },
        "property": "intAttr"
      },
      {
        "expression": {
          "type": "expression",
          "expression": "T(String).valueOf(object.longAttr)"
        },
        "property": "longAttr"
      },
      {
        "expression": {
          "type": "expression",
          "expression": "T(String).valueOf(object.bigDecimalAttr)"
        },
        "property": "bigDecimalAttr"
      }
    ]
  },
  "targets": [
    {
      "type": "property",
      "target": "TransformedObject"
    }
  ]
}